tno/mpc/protocols/kaplan_meier/__init__.py
tno/mpc/protocols/kaplan_meier/data_owner.py
tno/mpc/protocols/kaplan_meier/helper.py
tno/mpc/protocols/kaplan_meier/player.py
tno/mpc/protocols/kaplan_meier/py.typed
tno/mpc/protocols/kaplan_meier/test/__init__.py
tno/mpc/protocols/kaplan_meier/test/test_kaplan_meier.py
tno.mpc.protocols.kaplan_meier-1.0.4.dist-info/LICENSE
tno.mpc.protocols.kaplan_meier-1.0.4.dist-info/METADATA
tno.mpc.protocols.kaplan_meier-1.0.4.dist-info/WHEEL
tno.mpc.protocols.kaplan_meier-1.0.4.dist-info/top_level.txt
tno.mpc.protocols.kaplan_meier-1.0.4.dist-info/RECORD
