Metadata-Version: 2.1
Name: tno.mpc.protocols.kaplan_meier
Version: 1.0.4
Summary: Kaplan Meier using Paillier homomorphic encryption and a helper party
Author-email: TNO PET Lab <petlab@tno.nl>
Maintainer-email: TNO PET Lab <petlab@tno.nl>
License: Apache License, Version 2.0
Project-URL: Homepage, https://pet.tno.nl/
Project-URL: Documentation, https://docs.pet.tno.nl/mpc/protocols/kaplan_meier/1.0.4
Project-URL: Source, https://github.com/TNO-MPC/protocols.kaplan_meier
Keywords: TNO,MPC,multi-party computation,protocols,kaplan meier,survival analysis
Platform: any
Classifier: License :: OSI Approved :: Apache Software License
Classifier: Programming Language :: Python :: 3
Classifier: Operating System :: OS Independent
Classifier: Intended Audience :: Developers
Classifier: Intended Audience :: Healthcare Industry
Classifier: Intended Audience :: Information Technology
Classifier: Intended Audience :: Science/Research
Classifier: Typing :: Typed
Classifier: Topic :: Security :: Cryptography
Classifier: Topic :: Scientific/Engineering :: Medical Science Apps.
Requires-Python: >=3.8
License-File: LICENSE
Requires-Dist: lifelines~=0.27
Requires-Dist: mpyc~=0.7
Requires-Dist: numpy<2,>=1.24
Requires-Dist: pandas
Requires-Dist: scipy
Requires-Dist: tno.mpc.communication!=4.4.2,~=4.0
Requires-Dist: tno.mpc.encryption_schemes.paillier~=3.0
Requires-Dist: tno.mpc.encryption_schemes.utils~=0.6
Requires-Dist: tno.mpc.mpyc.matrix_inverse~=0.4
Provides-Extra: gmpy
Requires-Dist: tno.mpc.encryption_schemes.paillier[gmpy]; extra == "gmpy"
Requires-Dist: tno.mpc.encryption_schemes.utils[gmpy]; extra == "gmpy"
Requires-Dist: tno.mpc.mpyc.matrix_inverse[gmpy]; extra == "gmpy"
Provides-Extra: scripts
Requires-Dist: lifelines; extra == "scripts"
Provides-Extra: tests
Requires-Dist: pytest>=8.1; extra == "tests"
Requires-Dist: pytest-asyncio; extra == "tests"
Requires-Dist: tno.mpc.mpyc.stubs~=2.0; extra == "tests"
